{
  "title": "420 Evolution 33/1 CA ICC",
  "thc": {
    "value": 33.0,
    "unit": "%"
  },
  "cbd": {
    "value": 1.0,
    "unit": "%"
  },
  "price": {
    "value": {
      "value": 12.9,
      "unit": "g"
    }
  },
  "delivery_status": "lieferbar",
  "image_url": "https://medcanonestop.com/wp-content/uploads/2025/01/Four20_Evolution_Ice-Cream-Cake-Kush-Mints_ICC.png",
  "product_type": "Cannabisblüten",
  "timestamp": "2025-03-11T23:09:04.836550",
  "url": "https://medcanonestop.com/medcan_product/420-evolution-33-1-ca-icc/",
  "history": [
    {
      "title": "420 Evolution 33/1 CA ICC",
      "thc": {
        "value": 33.0,
        "unit": "%"
      },
      "cbd": {
        "value": 1.0,
        "unit": "%"
      },
      "price": {
        "value": {
          "value": 12.9,
          "unit": "g"
        }
      },
      "delivery_status": "lieferbar",
      "image_url": "https://medcanonestop.com/wp-content/uploads/2025/01/Four20_Evolution_Ice-Cream-Cake-Kush-Mints_ICC.png",
      "product_type": "Cannabisblüten",
      "timestamp": "2025-03-11T23:21:18.783302",
      "url": "https://medcanonestop.com/medcan_product/420-evolution-33-1-ca-icc/"
    },
    {
      "title": "420 Evolution 33/1 CA ICC",
      "thc": {
        "value": 33.0,
        "unit": "%"
      },
      "cbd": {
        "value": 1.0,
        "unit": "%"
      },
      "price": {
        "value": {
          "value": 12.9,
          "unit": "g"
        }
      },
      "delivery_status": "lieferbar",
      "image_url": "https://medcanonestop.com/wp-content/uploads/2025/01/Four20_Evolution_Ice-Cream-Cake-Kush-Mints_ICC.png",
      "product_type": "Cannabisblüten",
      "timestamp": "2025-03-11T23:50:27.108619",
      "url": "https://medcanonestop.com/medcan_product/420-evolution-33-1-ca-icc/"
    }
  ],
  "last_updated": "2025-03-11T23:50:27.108619"
}