{
  "title": "ADREX 21 LMOG COL",
  "thc": {
    "value": 21.0,
    "unit": "%"
  },
  "cbd": {
    "value": 1.0,
    "unit": "%"
  },
  "price": {
    "min": {
      "value": 6.65,
      "unit": "g"
    },
    "max": {
      "value": 7.29,
      "unit": "g"
    }
  },
  "delivery_status": "lieferbar",
  "image_url": "https://medcanonestop.com/wp-content/uploads/2024/01/761.png",
  "product_type": "Cannabisblüten",
  "timestamp": "2025-03-11T23:09:58.986249",
  "url": "https://medcanonestop.com/medcan_product/adrex-21-lmog-col-lemon-og/",
  "history": [
    {
      "title": "ADREX 21 LMOG COL",
      "thc": {
        "value": 21.0,
        "unit": "%"
      },
      "cbd": {
        "value": 1.0,
        "unit": "%"
      },
      "price": {
        "min": {
          "value": 6.65,
          "unit": "g"
        },
        "max": {
          "value": 7.29,
          "unit": "g"
        }
      },
      "delivery_status": "lieferbar",
      "image_url": "https://medcanonestop.com/wp-content/uploads/2024/01/761.png",
      "product_type": "Cannabisblüten",
      "timestamp": "2025-03-11T23:28:01.695151",
      "url": "https://medcanonestop.com/medcan_product/adrex-21-lmog-col-lemon-og/"
    },
    {
      "title": "ADREX 21 LMOG COL",
      "thc": {
        "value": 21.0,
        "unit": "%"
      },
      "cbd": {
        "value": 1.0,
        "unit": "%"
      },
      "price": {
        "min": {
          "value": 6.65,
          "unit": "g"
        },
        "max": {
          "value": 7.29,
          "unit": "g"
        }
      },
      "delivery_status": "lieferbar",
      "image_url": "https://medcanonestop.com/wp-content/uploads/2024/01/761.png",
      "product_type": "Cannabisblüten",
      "timestamp": "2025-03-11T23:44:25.506428",
      "url": "https://medcanonestop.com/medcan_product/adrex-21-lmog-col-lemon-og/"
    }
  ],
  "last_updated": "2025-03-11T23:44:25.506428"
}