{
  "title": "Adven 0/50",
  "thc": {
    "value": 0.0,
    "unit": "mg"
  },
  "cbd": {
    "value": 50.0,
    "unit": "mg"
  },
  "price": {
    "min": {
      "value": 9.99,
      "unit": "ml"
    },
    "max": {
      "value": 22.31,
      "unit": "ml"
    }
  },
  "delivery_status": "lieferbar",
  "image_url": "https://medcanonestop.com/wp-content/themes/medcanonestop/assets/img/extract-icon.svg",
  "product_type": "Cannabisblüten",
  "timestamp": "2025-03-11T23:07:15.246770",
  "url": "https://medcanonestop.com/medcan_product/adven-0-50/",
  "history": [
    {
      "title": "Adven 0/50",
      "thc": {
        "value": 0.0,
        "unit": "mg"
      },
      "cbd": {
        "value": 50.0,
        "unit": "mg"
      },
      "price": {
        "min": {
          "value": 9.99,
          "unit": "ml"
        },
        "max": {
          "value": 22.31,
          "unit": "ml"
        }
      },
      "delivery_status": "lieferbar",
      "image_url": "https://medcanonestop.com/wp-content/themes/medcanonestop/assets/img/extract-icon.svg",
      "product_type": "Cannabisblüten",
      "timestamp": "2025-03-11T23:22:06.856786",
      "url": "https://medcanonestop.com/medcan_product/adven-0-50/"
    },
    {
      "title": "Adven 0/50",
      "thc": {
        "value": 0.0,
        "unit": "mg"
      },
      "cbd": {
        "value": 50.0,
        "unit": "mg"
      },
      "price": {
        "min": {
          "value": 9.99,
          "unit": "ml"
        },
        "max": {
          "value": 22.31,
          "unit": "ml"
        }
      },
      "delivery_status": "lieferbar",
      "image_url": "https://medcanonestop.com/wp-content/themes/medcanonestop/assets/img/extract-icon.svg",
      "product_type": "Cannabisblüten",
      "timestamp": "2025-03-11T23:40:08.924138",
      "url": "https://medcanonestop.com/medcan_product/adven-0-50/"
    },
    {
      "title": "Adven 0/50",
      "thc": {
        "value": 0.0,
        "unit": "mg"
      },
      "cbd": {
        "value": 50.0,
        "unit": "mg"
      },
      "price": {
        "min": {
          "value": 9.99,
          "unit": "ml"
        },
        "max": {
          "value": 22.31,
          "unit": "ml"
        }
      },
      "delivery_status": "lieferbar",
      "image_url": "https://medcanonestop.com/wp-content/themes/medcanonestop/assets/img/extract-icon.svg",
      "product_type": "Cannabisblüten",
      "timestamp": "2025-03-12T00:26:27.145792",
      "url": "https://medcanonestop.com/medcan_product/adven-0-50/"
    },
    {
      "title": "Adven 0/50",
      "thc": {
        "value": 0.0,
        "unit": "mg"
      },
      "cbd": {
        "value": 50.0,
        "unit": "mg"
      },
      "price": {
        "min": {
          "value": 9.99,
          "unit": "ml"
        },
        "max": {
          "value": 22.31,
          "unit": "ml"
        }
      },
      "delivery_status": "lieferbar",
      "image_url": "https://medcanonestop.com/wp-content/themes/medcanonestop/assets/img/extract-icon.svg",
      "product_type": "Cannabisblüten",
      "timestamp": "2025-03-12T00:32:43.110453",
      "url": "https://medcanonestop.com/medcan_product/adven-0-50/"
    },
    {
      "title": "Adven 0/50",
      "thc": {
        "value": 0.0,
        "unit": "mg"
      },
      "cbd": {
        "value": 50.0,
        "unit": "mg"
      },
      "price": {
        "min": {
          "value": 9.99,
          "unit": "ml"
        },
        "max": {
          "value": 22.31,
          "unit": "ml"
        }
      },
      "delivery_status": "lieferbar",
      "image_url": "https://medcanonestop.com/wp-content/themes/medcanonestop/assets/img/extract-icon.svg",
      "product_type": "Cannabisblüten",
      "timestamp": "2025-03-12T00:53:05.958086",
      "url": "https://medcanonestop.com/medcan_product/adven-0-50/"
    },
    {
      "title": "Adven 0/50",
      "thc": {
        "value": 0.0,
        "unit": "mg"
      },
      "cbd": {
        "value": 50.0,
        "unit": "mg"
      },
      "price": {
        "min": {
          "value": 9.99,
          "unit": "ml"
        },
        "max": {
          "value": 22.31,
          "unit": "ml"
        }
      },
      "delivery_status": "lieferbar",
      "image_url": "https://medcanonestop.com/wp-content/themes/medcanonestop/assets/img/extract-icon.svg",
      "product_type": "Cannabisblüten",
      "timestamp": "2025-03-12T02:03:53.405339",
      "url": "https://medcanonestop.com/medcan_product/adven-0-50/"
    },
    {
      "title": "Adven 0/50",
      "thc": {
        "value": 0.0,
        "unit": "mg"
      },
      "cbd": {
        "value": 50.0,
        "unit": "mg"
      },
      "price": {
        "min": {
          "value": 9.99,
          "unit": "ml"
        },
        "max": {
          "value": 22.31,
          "unit": "ml"
        }
      },
      "delivery_status": "lieferbar",
      "image_url": "https://medcanonestop.com/wp-content/themes/medcanonestop/assets/img/extract-icon.svg",
      "product_type": "Cannabisblüten",
      "timestamp": "2025-03-12T02:33:18.725116",
      "url": "https://medcanonestop.com/medcan_product/adven-0-50/"
    },
    {
      "title": "Adven 0/50",
      "thc": {
        "value": 0.0,
        "unit": "mg"
      },
      "cbd": {
        "value": 50.0,
        "unit": "mg"
      },
      "price": {
        "min": {
          "value": 9.99,
          "unit": "ml"
        },
        "max": {
          "value": 22.31,
          "unit": "ml"
        }
      },
      "delivery_status": "lieferbar",
      "image_url": "https://medcanonestop.com/wp-content/themes/medcanonestop/assets/img/extract-icon.svg",
      "product_type": "Cannabisblüten",
      "timestamp": "2025-03-12T03:39:46.693704",
      "url": "https://medcanonestop.com/medcan_product/adven-0-50/"
    },
    {
      "title": "Adven 0/50",
      "thc": {
        "value": 0.0,
        "unit": "mg"
      },
      "cbd": {
        "value": 50.0,
        "unit": "mg"
      },
      "price": {
        "min": {
          "value": 9.99,
          "unit": "ml"
        },
        "max": {
          "value": 22.31,
          "unit": "ml"
        }
      },
      "delivery_status": "lieferbar",
      "image_url": "https://medcanonestop.com/wp-content/themes/medcanonestop/assets/img/extract-icon.svg",
      "product_type": "Cannabisblüten",
      "timestamp": "2025-03-12T04:46:48.680662",
      "url": "https://medcanonestop.com/medcan_product/adven-0-50/"
    },
    {
      "title": "Adven 0/50",
      "thc": {
        "value": 0.0,
        "unit": "mg"
      },
      "cbd": {
        "value": 50.0,
        "unit": "mg"
      },
      "price": {
        "min": {
          "value": 9.99,
          "unit": "ml"
        },
        "max": {
          "value": 22.31,
          "unit": "ml"
        }
      },
      "delivery_status": "lieferbar",
      "image_url": "https://medcanonestop.com/wp-content/themes/medcanonestop/assets/img/extract-icon.svg",
      "product_type": "Cannabisblüten",
      "timestamp": "2025-03-12T09:56:17.094277",
      "url": "https://medcanonestop.com/medcan_product/adven-0-50/"
    },
    {
      "title": "Adven 0/50",
      "thc": {
        "value": 0.0,
        "unit": "mg"
      },
      "cbd": {
        "value": 50.0,
        "unit": "mg"
      },
      "price": {
        "min": {
          "value": 9.99,
          "unit": "ml"
        },
        "max": {
          "value": 22.31,
          "unit": "ml"
        }
      },
      "delivery_status": "lieferbar",
      "image_url": "https://medcanonestop.com/wp-content/themes/medcanonestop/assets/img/extract-icon.svg",
      "product_type": "Cannabisblüten",
      "timestamp": "2025-03-12T11:01:56.719326",
      "url": "https://medcanonestop.com/medcan_product/adven-0-50/"
    },
    {
      "title": "Adven 0/50",
      "thc": {
        "value": 0.0,
        "unit": "mg"
      },
      "cbd": {
        "value": 50.0,
        "unit": "mg"
      },
      "price": {
        "min": {
          "value": 9.99,
          "unit": "ml"
        },
        "max": {
          "value": 22.31,
          "unit": "ml"
        }
      },
      "delivery_status": "lieferbar",
      "image_url": "https://medcanonestop.com/wp-content/themes/medcanonestop/assets/img/extract-icon.svg",
      "product_type": "Cannabisblüten",
      "timestamp": "2025-03-12T12:11:17.836645",
      "url": "https://medcanonestop.com/medcan_product/adven-0-50/"
    },
    {
      "title": "Adven 0/50",
      "thc": {
        "value": 0.0,
        "unit": "mg"
      },
      "cbd": {
        "value": 50.0,
        "unit": "mg"
      },
      "price": {
        "min": {
          "value": 9.99,
          "unit": "ml"
        },
        "max": {
          "value": 22.31,
          "unit": "ml"
        }
      },
      "delivery_status": "lieferbar",
      "image_url": "https://medcanonestop.com/wp-content/themes/medcanonestop/assets/img/extract-icon.svg",
      "product_type": "Cannabisblüten",
      "timestamp": "2025-03-12T13:18:51.554330",
      "url": "https://medcanonestop.com/medcan_product/adven-0-50/"
    }
  ],
  "last_updated": "2025-03-12T13:18:51.554330"
}