[
  {
    "title": "aleph earth 19/1",
    "category": "Hybrid",
    "thc": 19.0,
    "cbd": 1.0,
    "attributes": {
      "Bestrahlung": "Unbestrahlt",
      "Kultivar": "KO Kush x Sherbert PT",
      "Herkunft": "",
      "Importeur": "alephSana",
      "Anbauer": ""
    },
    "price": {
      "min": 6.59,
      "max": 8.0
    },
    "ratings": {
      "Aussehen": 3.5,
      "Aroma": 3.6,
      "Geschmack": 3.7,
      "Effekt": 4.0,
      "Gesamt": 3.7
    },
    "effects": [
      "Begeistert",
      "Entspannt",
      "Fröhlich"
    ],
    "aroma": [
      "Erdig",
      "Floral",
      "Lemon"
    ],
    "terpenes": [
      {
        "code": "LI",
        "name": "Limonen"
      },
      {
        "code": "MY",
        "name": "Myrcen"
      },
      {
        "code": "β",
        "name": "β-Caryophyllen"
      }
    ],
    "medical_uses": [
      "Angstlösend",
      "Muskelentspannend",
      "Stimmungsaufhellend"
    ],
    "delivery_status": "lieferbar",
    "image_url": "https://medcanonestop.com/wp-content/uploads/2025/01/aleph-earth.png",
    "product_type": "Cannabisblüten",
    "timestamp": "2025-03-11T13:41:37.017736",
    "url": "https://medcanonestop.com/medcan_product/aleph-earth-19-1/",
    "image_path": "images\\aleph-earth.png"
  }
]