[
  {
    "title": "Cannamedical Cannabisextrakt THC20:CBD20",
    "category": "Sativa",
    "thc": 0.0,
    "cbd": 0.0,
    "attributes": {
      "Extraktionsverfahren": "CO2",
      "Trägeröl": "MCT-Öl",
      "Kultivar": "Gelato Dream",
      "Herkunft": "Nordmazedonien",
      "Hersteller": "Cannamedical"
    },
    "price": {
      "min": 6.69,
      "max": 139.9
    },
    "ratings": {
      "Aussehen": 4.0,
      "Aroma": 3.3,
      "Geschmack": 3.3,
      "Effekt": 4.3,
      "Gesamt": 3.7
    },
    "effects": [],
    "aroma": [],
    "terpenes": [],
    "medical_uses": [],
    "delivery_status": "lieferbar",
    "image_url": "https://medcanonestop.com/wp-content/uploads/2024/05/Cannamedical-Cannabisextrakt-THC20_CBD20.jpg",
    "product_type": "Cannabisblüten",
    "timestamp": "2025-03-11T13:42:35.868741",
    "url": "https://medcanonestop.com/medcan_product/cannamedical-thc20cbd20/",
    "image_path": "images\\Cannamedical-Cannabisextrakt-THC20_CBD20.jpg"
  }
]