{
  "title": "Cannamedical indica forte: EJ Vollspektrumextrakt 25mg/ml",
  "thc": {
    "value": 25.0,
    "unit": "mg"
  },
  "cbd": {
    "value": 0.0,
    "unit": "mg"
  },
  "price": {
    "value": {
      "value": 3.96,
      "unit": "ml"
    }
  },
  "delivery_status": "lieferbar",
  "image_url": "https://medcanonestop.com/wp-content/themes/medcanonestop/assets/img/extract-icon.svg",
  "product_type": "Cannabisblüten",
  "timestamp": "2025-03-11T23:08:27.806935",
  "url": "https://medcanonestop.com/medcan_product/cannamedical-indica-forte-el-jefe-vollspektrumextrakt-25mg-ml/",
  "history": [
    {
      "title": "Cannamedical indica forte: EJ Vollspektrumextrakt 25mg/ml",
      "thc": {
        "value": 25.0,
        "unit": "mg"
      },
      "cbd": {
        "value": 0.0,
        "unit": "mg"
      },
      "price": {
        "value": {
          "value": 3.96,
          "unit": "ml"
        }
      },
      "delivery_status": "lieferbar",
      "image_url": "https://medcanonestop.com/wp-content/themes/medcanonestop/assets/img/extract-icon.svg",
      "product_type": "Cannabisblüten",
      "timestamp": "2025-03-11T23:13:06.578706",
      "url": "https://medcanonestop.com/medcan_product/cannamedical-indica-forte-el-jefe-vollspektrumextrakt-25mg-ml/"
    },
    {
      "title": "Cannamedical indica forte: EJ Vollspektrumextrakt 25mg/ml",
      "thc": {
        "value": 25.0,
        "unit": "mg"
      },
      "cbd": {
        "value": 0.0,
        "unit": "mg"
      },
      "price": {
        "value": {
          "value": 3.96,
          "unit": "ml"
        }
      },
      "delivery_status": "lieferbar",
      "image_url": "https://medcanonestop.com/wp-content/themes/medcanonestop/assets/img/extract-icon.svg",
      "product_type": "Cannabisblüten",
      "timestamp": "2025-03-11T23:24:22.394653",
      "url": "https://medcanonestop.com/medcan_product/cannamedical-indica-forte-el-jefe-vollspektrumextrakt-25mg-ml/"
    },
    {
      "title": "Cannamedical indica forte: EJ Vollspektrumextrakt 25mg/ml",
      "thc": {
        "value": 25.0,
        "unit": "mg"
      },
      "cbd": {
        "value": 0.0,
        "unit": "mg"
      },
      "price": {
        "value": {
          "value": 3.96,
          "unit": "ml"
        }
      },
      "delivery_status": "lieferbar",
      "image_url": "https://medcanonestop.com/wp-content/themes/medcanonestop/assets/img/extract-icon.svg",
      "product_type": "Cannabisblüten",
      "timestamp": "2025-03-12T00:10:30.052904",
      "url": "https://medcanonestop.com/medcan_product/cannamedical-indica-forte-el-jefe-vollspektrumextrakt-25mg-ml/"
    },
    {
      "title": "Cannamedical indica forte: EJ Vollspektrumextrakt 25mg/ml",
      "thc": {
        "value": 25.0,
        "unit": "mg"
      },
      "cbd": {
        "value": 0.0,
        "unit": "mg"
      },
      "price": {
        "value": {
          "value": 3.96,
          "unit": "ml"
        }
      },
      "delivery_status": "lieferbar",
      "image_url": "https://medcanonestop.com/wp-content/themes/medcanonestop/assets/img/extract-icon.svg",
      "product_type": "Cannabisblüten",
      "timestamp": "2025-03-12T00:48:29.536949",
      "url": "https://medcanonestop.com/medcan_product/cannamedical-indica-forte-el-jefe-vollspektrumextrakt-25mg-ml/"
    },
    {
      "title": "Cannamedical indica forte: EJ Vollspektrumextrakt 25mg/ml",
      "thc": {
        "value": 25.0,
        "unit": "mg"
      },
      "cbd": {
        "value": 0.0,
        "unit": "mg"
      },
      "price": {
        "value": {
          "value": 3.96,
          "unit": "ml"
        }
      },
      "delivery_status": "lieferbar",
      "image_url": "https://medcanonestop.com/wp-content/themes/medcanonestop/assets/img/extract-icon.svg",
      "product_type": "Cannabisblüten",
      "timestamp": "2025-03-12T00:53:44.040328",
      "url": "https://medcanonestop.com/medcan_product/cannamedical-indica-forte-el-jefe-vollspektrumextrakt-25mg-ml/"
    },
    {
      "title": "Cannamedical indica forte: EJ Vollspektrumextrakt 25mg/ml",
      "thc": {
        "value": 25.0,
        "unit": "mg"
      },
      "cbd": {
        "value": 0.0,
        "unit": "mg"
      },
      "price": {
        "value": {
          "value": 3.96,
          "unit": "ml"
        }
      },
      "delivery_status": "lieferbar",
      "image_url": "https://medcanonestop.com/wp-content/themes/medcanonestop/assets/img/extract-icon.svg",
      "product_type": "Cannabisblüten",
      "timestamp": "2025-03-12T02:33:25.850649",
      "url": "https://medcanonestop.com/medcan_product/cannamedical-indica-forte-el-jefe-vollspektrumextrakt-25mg-ml/"
    },
    {
      "title": "Cannamedical indica forte: EJ Vollspektrumextrakt 25mg/ml",
      "thc": {
        "value": 25.0,
        "unit": "mg"
      },
      "cbd": {
        "value": 0.0,
        "unit": "mg"
      },
      "price": {
        "value": {
          "value": 3.96,
          "unit": "ml"
        }
      },
      "delivery_status": "lieferbar",
      "image_url": "https://medcanonestop.com/wp-content/themes/medcanonestop/assets/img/extract-icon.svg",
      "product_type": "Cannabisblüten",
      "timestamp": "2025-03-12T03:39:55.556181",
      "url": "https://medcanonestop.com/medcan_product/cannamedical-indica-forte-el-jefe-vollspektrumextrakt-25mg-ml/"
    },
    {
      "title": "Cannamedical indica forte: EJ Vollspektrumextrakt 25mg/ml",
      "thc": {
        "value": 25.0,
        "unit": "mg"
      },
      "cbd": {
        "value": 0.0,
        "unit": "mg"
      },
      "price": {
        "value": {
          "value": 3.96,
          "unit": "ml"
        }
      },
      "delivery_status": "lieferbar",
      "image_url": "https://medcanonestop.com/wp-content/themes/medcanonestop/assets/img/extract-icon.svg",
      "product_type": "Cannabisblüten",
      "timestamp": "2025-03-12T04:46:57.820710",
      "url": "https://medcanonestop.com/medcan_product/cannamedical-indica-forte-el-jefe-vollspektrumextrakt-25mg-ml/"
    },
    {
      "title": "Cannamedical indica forte: EJ Vollspektrumextrakt 25mg/ml",
      "thc": {
        "value": 25.0,
        "unit": "mg"
      },
      "cbd": {
        "value": 0.0,
        "unit": "mg"
      },
      "price": {
        "value": {
          "value": 3.96,
          "unit": "ml"
        }
      },
      "delivery_status": "lieferbar",
      "image_url": "https://medcanonestop.com/wp-content/themes/medcanonestop/assets/img/extract-icon.svg",
      "product_type": "Cannabisblüten",
      "timestamp": "2025-03-12T10:00:24.905558",
      "url": "https://medcanonestop.com/medcan_product/cannamedical-indica-forte-el-jefe-vollspektrumextrakt-25mg-ml/"
    },
    {
      "title": "Cannamedical indica forte: EJ Vollspektrumextrakt 25mg/ml",
      "thc": {
        "value": 25.0,
        "unit": "mg"
      },
      "cbd": {
        "value": 0.0,
        "unit": "mg"
      },
      "price": {
        "value": {
          "value": 3.96,
          "unit": "ml"
        }
      },
      "delivery_status": "lieferbar",
      "image_url": "https://medcanonestop.com/wp-content/themes/medcanonestop/assets/img/extract-icon.svg",
      "product_type": "Cannabisblüten",
      "timestamp": "2025-03-12T11:08:27.603064",
      "url": "https://medcanonestop.com/medcan_product/cannamedical-indica-forte-el-jefe-vollspektrumextrakt-25mg-ml/"
    },
    {
      "title": "Cannamedical indica forte: EJ Vollspektrumextrakt 25mg/ml",
      "thc": {
        "value": 25.0,
        "unit": "mg"
      },
      "cbd": {
        "value": 0.0,
        "unit": "mg"
      },
      "price": {
        "value": {
          "value": 3.96,
          "unit": "ml"
        }
      },
      "delivery_status": "lieferbar",
      "image_url": "https://medcanonestop.com/wp-content/themes/medcanonestop/assets/img/extract-icon.svg",
      "product_type": "Cannabisblüten",
      "timestamp": "2025-03-12T12:08:21.360100",
      "url": "https://medcanonestop.com/medcan_product/cannamedical-indica-forte-el-jefe-vollspektrumextrakt-25mg-ml/"
    },
    {
      "title": "Cannamedical indica forte: EJ Vollspektrumextrakt 25mg/ml",
      "thc": {
        "value": 25.0,
        "unit": "mg"
      },
      "cbd": {
        "value": 0.0,
        "unit": "mg"
      },
      "price": {
        "value": {
          "value": 3.96,
          "unit": "ml"
        }
      },
      "delivery_status": "lieferbar",
      "image_url": "https://medcanonestop.com/wp-content/themes/medcanonestop/assets/img/extract-icon.svg",
      "product_type": "Cannabisblüten",
      "timestamp": "2025-03-12T13:15:53.649299",
      "url": "https://medcanonestop.com/medcan_product/cannamedical-indica-forte-el-jefe-vollspektrumextrakt-25mg-ml/"
    },
    {
      "title": "Cannamedical indica forte: EJ Vollspektrumextrakt 25mg/ml",
      "thc": {
        "value": 25.0,
        "unit": "mg"
      },
      "cbd": {
        "value": 0.0,
        "unit": "mg"
      },
      "price": {
        "value": {
          "value": 3.96,
          "unit": "ml"
        }
      },
      "delivery_status": "lieferbar",
      "image_url": "https://medcanonestop.com/wp-content/themes/medcanonestop/assets/img/extract-icon.svg",
      "product_type": "Cannabisblüten",
      "timestamp": "2025-03-12T14:24:06.123064",
      "url": "https://medcanonestop.com/medcan_product/cannamedical-indica-forte-el-jefe-vollspektrumextrakt-25mg-ml/"
    }
  ],
  "last_updated": "2025-03-12T14:24:06.123064"
}