{
  "title": "Cannamedical Hybrid forte DK GTH",
  "thc": {
    "value": 22.0,
    "unit": "%"
  },
  "cbd": {
    "value": 1.0,
    "unit": "%"
  },
  "price": {
    "min": {
      "value": 7.99,
      "unit": "g"
    },
    "max": {
      "value": 13.68,
      "unit": "g"
    }
  },
  "delivery_status": "lieferbar",
  "image_url": "https://medcanonestop.com/wp-content/uploads/2024/11/6838.png",
  "product_type": "Cannabisblüten",
  "timestamp": "2025-03-11T23:11:06.804973",
  "url": "https://medcanonestop.com/medcan_product/cannamedical-hybrid-forte-dk-gth/",
  "history": [
    {
      "title": "Cannamedical Hybrid forte DK GTH",
      "thc": {
        "value": 22.0,
        "unit": "%"
      },
      "cbd": {
        "value": 1.0,
        "unit": "%"
      },
      "price": {
        "min": {
          "value": 7.99,
          "unit": "g"
        },
        "max": {
          "value": 13.68,
          "unit": "g"
        }
      },
      "delivery_status": "lieferbar",
      "image_url": "https://medcanonestop.com/wp-content/uploads/2024/11/6838.png",
      "product_type": "Cannabisblüten",
      "timestamp": "2025-03-11T23:40:29.459112",
      "url": "https://medcanonestop.com/medcan_product/cannamedical-hybrid-forte-dk-gth/"
    }
  ],
  "last_updated": "2025-03-11T23:40:29.459112"
}