{
  "title": "Cannamedical Indica classic ZAF  DW",
  "url": "https://medcanonestop.com/medcan_product/cannamedical-indica-classic-zaf-dw/",
  "product_type": "Cannabisblüten",
  "last_updated": "2025-03-12T09:56:27.043762",
  "history": [
    {
      "title": "Cannamedical Indica classic ZAF  DW",
      "thc": {
        "value": 20.0,
        "unit": "%"
      },
      "cbd": {
        "value": 1.0,
        "unit": "%"
      },
      "price": {
        "min": {
          "value": 6.39,
          "unit": "g"
        },
        "max": {
          "value": 14.7,
          "unit": "g"
        }
      },
      "delivery_status": "lieferbar",
      "image_url": "https://medcanonestop.com/wp-content/uploads/2024/10/Dank-Wafers.png",
      "product_type": "Cannabisblüten",
      "timestamp": "2025-03-11T23:24:51.825019",
      "url": "https://medcanonestop.com/medcan_product/cannamedical-indica-classic-zaf-dw/"
    },
    {
      "title": "Cannamedical Indica classic ZAF  DW",
      "thc": {
        "value": 20.0,
        "unit": "%"
      },
      "cbd": {
        "value": 1.0,
        "unit": "%"
      },
      "price": {
        "min": {
          "value": 6.39,
          "unit": "g"
        },
        "max": {
          "value": 14.7,
          "unit": "g"
        }
      },
      "delivery_status": "lieferbar",
      "image_url": "https://medcanonestop.com/wp-content/uploads/2024/10/Dank-Wafers.png",
      "product_type": "Cannabisblüten",
      "timestamp": "2025-03-11T23:43:20.719906",
      "url": "https://medcanonestop.com/medcan_product/cannamedical-indica-classic-zaf-dw/"
    },
    {
      "title": "Cannamedical Indica classic ZAF  DW",
      "thc": {
        "value": 20.0,
        "unit": "%"
      },
      "cbd": {
        "value": 1.0,
        "unit": "%"
      },
      "price": {
        "min": {
          "value": 6.39,
          "unit": "g"
        },
        "max": {
          "value": 14.7,
          "unit": "g"
        }
      },
      "delivery_status": "lieferbar",
      "image_url": "https://medcanonestop.com/wp-content/uploads/2024/10/Dank-Wafers.png",
      "product_type": "Cannabisblüten",
      "timestamp": "2025-03-12T00:12:50.473781",
      "url": "https://medcanonestop.com/medcan_product/cannamedical-indica-classic-zaf-dw/"
    },
    {
      "title": "Cannamedical Indica classic ZAF  DW",
      "thc": {
        "value": 20.0,
        "unit": "%"
      },
      "cbd": {
        "value": 1.0,
        "unit": "%"
      },
      "price": {
        "min": {
          "value": 6.39,
          "unit": "g"
        },
        "max": {
          "value": 14.7,
          "unit": "g"
        }
      },
      "delivery_status": "lieferbar",
      "image_url": "https://medcanonestop.com/wp-content/uploads/2024/10/Dank-Wafers.png",
      "product_type": "Cannabisblüten",
      "timestamp": "2025-03-12T00:31:56.771708",
      "url": "https://medcanonestop.com/medcan_product/cannamedical-indica-classic-zaf-dw/"
    },
    {
      "title": "Cannamedical Indica classic ZAF  DW",
      "thc": {
        "value": 20.0,
        "unit": "%"
      },
      "cbd": {
        "value": 1.0,
        "unit": "%"
      },
      "price": {
        "min": {
          "value": 6.39,
          "unit": "g"
        },
        "max": {
          "value": 14.7,
          "unit": "g"
        }
      },
      "delivery_status": "lieferbar",
      "image_url": "https://medcanonestop.com/wp-content/uploads/2024/10/Dank-Wafers.png",
      "product_type": "Cannabisblüten",
      "timestamp": "2025-03-12T00:51:28.407616",
      "url": "https://medcanonestop.com/medcan_product/cannamedical-indica-classic-zaf-dw/"
    },
    {
      "title": "Cannamedical Indica classic ZAF  DW",
      "thc": {
        "value": 20.0,
        "unit": "%"
      },
      "cbd": {
        "value": 1.0,
        "unit": "%"
      },
      "price": {
        "min": {
          "value": 6.39,
          "unit": "g"
        },
        "max": {
          "value": 14.7,
          "unit": "g"
        }
      },
      "delivery_status": "lieferbar",
      "image_url": "https://medcanonestop.com/wp-content/uploads/2024/10/Dank-Wafers.png",
      "product_type": "Cannabisblüten",
      "timestamp": "2025-03-12T02:21:53.481393",
      "url": "https://medcanonestop.com/medcan_product/cannamedical-indica-classic-zaf-dw/"
    },
    {
      "title": "Cannamedical Indica classic ZAF  DW",
      "thc": {
        "value": 20.0,
        "unit": "%"
      },
      "cbd": {
        "value": 1.0,
        "unit": "%"
      },
      "price": {
        "min": {
          "value": 6.39,
          "unit": "g"
        },
        "max": {
          "value": 14.7,
          "unit": "g"
        }
      },
      "delivery_status": "lieferbar",
      "image_url": "https://medcanonestop.com/wp-content/uploads/2024/10/Dank-Wafers.png",
      "product_type": "Cannabisblüten",
      "timestamp": "2025-03-12T02:33:59.512528",
      "url": "https://medcanonestop.com/medcan_product/cannamedical-indica-classic-zaf-dw/"
    },
    {
      "title": "Cannamedical Indica classic ZAF  DW",
      "thc": {
        "value": 20.0,
        "unit": "%"
      },
      "cbd": {
        "value": 1.0,
        "unit": "%"
      },
      "price": {
        "min": {
          "value": 6.39,
          "unit": "g"
        },
        "max": {
          "value": 14.7,
          "unit": "g"
        }
      },
      "delivery_status": "lieferbar",
      "image_url": "https://medcanonestop.com/wp-content/uploads/2024/10/Dank-Wafers.png",
      "product_type": "Cannabisblüten",
      "timestamp": "2025-03-12T03:40:40.204752",
      "url": "https://medcanonestop.com/medcan_product/cannamedical-indica-classic-zaf-dw/"
    },
    {
      "title": "Cannamedical Indica classic ZAF  DW",
      "thc": {
        "value": 20.0,
        "unit": "%"
      },
      "cbd": {
        "value": 1.0,
        "unit": "%"
      },
      "price": {
        "min": {
          "value": 6.39,
          "unit": "g"
        },
        "max": {
          "value": 14.7,
          "unit": "g"
        }
      },
      "delivery_status": "lieferbar",
      "image_url": "https://medcanonestop.com/wp-content/uploads/2024/10/Dank-Wafers.png",
      "product_type": "Cannabisblüten",
      "timestamp": "2025-03-12T04:47:45.240874",
      "url": "https://medcanonestop.com/medcan_product/cannamedical-indica-classic-zaf-dw/"
    },
    {
      "title": "Cannamedical Indica classic ZAF  DW",
      "thc": {
        "value": 20.0,
        "unit": "%"
      },
      "cbd": {
        "value": 1.0,
        "unit": "%"
      },
      "price": {
        "min": {
          "value": 6.39,
          "unit": "g"
        },
        "max": {
          "value": 14.7,
          "unit": "g"
        }
      },
      "delivery_status": "lieferbar",
      "image_url": "https://medcanonestop.com/wp-content/uploads/2024/10/Dank-Wafers.png",
      "product_type": "Cannabisblüten",
      "timestamp": "2025-03-12T09:56:27.043762",
      "url": "https://medcanonestop.com/medcan_product/cannamedical-indica-classic-zaf-dw/"
    }
  ]
}