{
  "title": "Drapalin 26/1 Oreoz",
  "thc": {
    "value": 26.0,
    "unit": "%"
  },
  "cbd": {
    "value": 1.0,
    "unit": "%"
  },
  "price": {
    "value": {
      "value": 9.5,
      "unit": "g"
    }
  },
  "delivery_status": "lieferbar",
  "image_url": "https://medcanonestop.com/wp-content/uploads/2024/05/Drapalin_Oreoz-2.png",
  "product_type": "Cannabisbl端ten",
  "timestamp": "2025-03-11T23:08:20.818581",
  "url": "https://medcanonestop.com/medcan_product/drapalin-26-1-oreoz/",
  "history": [
    {
      "title": "Drapalin 26/1 Oreoz",
      "thc": {
        "value": 26.0,
        "unit": "%"
      },
      "cbd": {
        "value": 1.0,
        "unit": "%"
      },
      "price": {
        "value": {
          "value": 9.5,
          "unit": "g"
        }
      },
      "delivery_status": "lieferbar",
      "image_url": "https://medcanonestop.com/wp-content/uploads/2024/05/Drapalin_Oreoz-2.png",
      "product_type": "Cannabisbl端ten",
      "timestamp": "2025-03-11T23:16:05.133613",
      "url": "https://medcanonestop.com/medcan_product/drapalin-26-1-oreoz/"
    },
    {
      "title": "Drapalin 26/1 Oreoz",
      "thc": {
        "value": 26.0,
        "unit": "%"
      },
      "cbd": {
        "value": 1.0,
        "unit": "%"
      },
      "price": {
        "value": {
          "value": 9.5,
          "unit": "g"
        }
      },
      "delivery_status": "lieferbar",
      "image_url": "https://medcanonestop.com/wp-content/uploads/2024/05/Drapalin_Oreoz-2.png",
      "product_type": "Cannabisbl端ten",
      "timestamp": "2025-03-11T23:24:48.427118",
      "url": "https://medcanonestop.com/medcan_product/drapalin-26-1-oreoz/"
    },
    {
      "title": "Drapalin 26/1 Oreoz",
      "thc": {
        "value": 26.0,
        "unit": "%"
      },
      "cbd": {
        "value": 1.0,
        "unit": "%"
      },
      "price": {
        "value": {
          "value": 9.5,
          "unit": "g"
        }
      },
      "delivery_status": "lieferbar",
      "image_url": "https://medcanonestop.com/wp-content/uploads/2024/05/Drapalin_Oreoz-2.png",
      "product_type": "Cannabisbl端ten",
      "timestamp": "2025-03-11T23:39:42.779801",
      "url": "https://medcanonestop.com/medcan_product/drapalin-26-1-oreoz/"
    }
  ],
  "last_updated": "2025-03-11T23:39:42.779801"
}