[
  {
    "title": "LOT 420 AB 25/1",
    "category": "Hybrid",
    "thc": 24.1,
    "cbd": 1.0,
    "attributes": {
      "Bestrahlung": "Unbestrahlt",
      "Kultivar": "Apples & Bananas",
      "Herkunft": "Kanada",
      "Importeur": "Cantourage",
      "Anbauer": "LOT 420"
    },
    "price": {
      "min": 9.99,
      "max": 12.35
    },
    "ratings": {
      "Aussehen": 4.3,
      "Aroma": 4.4,
      "Geschmack": 4.2,
      "Effekt": 4.4,
      "Gesamt": 4.3
    },
    "effects": [
      "Aktiv",
      "Fröhlich",
      "Gesprächig"
    ],
    "aroma": [
      "Diesel",
      "Floral",
      "Fruchtig"
    ],
    "terpenes": [
      {
        "code": "CA",
        "name": "Caryophyllen"
      },
      {
        "code": "MY",
        "name": "Myrcen"
      },
      {
        "code": "OC",
        "name": "Ocimen"
      }
    ],
    "medical_uses": [
      "Angstlösend",
      "Stimmungsaufhellend",
      "Stressabbauend"
    ],
    "delivery_status": "lieferbar",
    "image_url": "https://medcanonestop.com/wp-content/uploads/2024/09/LOT420_AB.png",
    "product_type": "Cannabisblüten",
    "timestamp": "2025-03-11T13:43:01.444180",
    "url": "https://medcanonestop.com/medcan_product/lot-420-ab-25-1/",
    "image_path": "images\\LOT420_AB.png"
  }
]