[
  {
    "title": "LOT 420 MLND PT",
    "category": "Sativa",
    "thc": 20.8,
    "cbd": 1.0,
    "attributes": {
      "Bestrahlung": "Unbestrahlt",
      "Kultivar": "Melonade",
      "Herkunft": "Kanada",
      "Importeur": "Cantourage",
      "Anbauer": ""
    },
    "price": {
      "min": 8.48,
      "max": 11.89
    },
    "ratings": {
      "Aussehen": 4.3,
      "Aroma": 4.2,
      "Geschmack": 4.1,
      "Effekt": 4.3,
      "Gesamt": 4.2
    },
    "effects": [
      "Entspannt",
      "Fröhlich",
      "Gesprächig"
    ],
    "aroma": [
      "Cremig",
      "Diesel",
      "Lemon"
    ],
    "terpenes": [
      {
        "code": "CA",
        "name": "Caryophyllen"
      },
      {
        "code": "FA",
        "name": "Farnesen"
      },
      {
        "code": "MY",
        "name": "Myrcen"
      }
    ],
    "medical_uses": [
      "Entzündungshemmend",
      "Muskelentspannend",
      "Schmerzstillend",
      "Stimmungsaufhellend"
    ],
    "delivery_status": "lieferbar",
    "image_url": "https://medcanonestop.com/wp-content/uploads/2024/09/LOT420_Melonade.png",
    "product_type": "Cannabisblüten",
    "timestamp": "2025-03-11T13:45:49.383745",
    "url": "https://medcanonestop.com/medcan_product/lot-420-mlnd/",
    "image_path": "images\\LOT420_Melonade.png"
  }
]