{
  "title": "Nimbus 26/1 ZRP",
  "thc": {
    "value": 26.0,
    "unit": "%"
  },
  "cbd": {
    "value": 1.0,
    "unit": "%"
  },
  "price": {
    "value": {
      "value": null,
      "unit": null
    }
  },
  "delivery_status": "Unbekannt",
  "image_url": "https://medcanonestop.com/wp-content/themes/medcanonestop/assets/img/flower-icon.svg",
  "product_type": "Cannabisblüten",
  "timestamp": "2025-03-11T23:08:25.848866",
  "url": "https://medcanonestop.com/medcan_product/nimbus-26-1-zrp/",
  "history": [
    {
      "title": "Nimbus 26/1 ZRP",
      "thc": {
        "value": 26.0,
        "unit": "%"
      },
      "cbd": {
        "value": 1.0,
        "unit": "%"
      },
      "price": {
        "value": {
          "value": null,
          "unit": null
        }
      },
      "delivery_status": "Unbekannt",
      "image_url": "https://medcanonestop.com/wp-content/themes/medcanonestop/assets/img/flower-icon.svg",
      "product_type": "Cannabisblüten",
      "timestamp": "2025-03-11T23:18:31.823953",
      "url": "https://medcanonestop.com/medcan_product/nimbus-26-1-zrp/"
    },
    {
      "title": "Nimbus 26/1 ZRP",
      "thc": {
        "value": 26.0,
        "unit": "%"
      },
      "cbd": {
        "value": 1.0,
        "unit": "%"
      },
      "price": {
        "value": {
          "value": null,
          "unit": null
        }
      },
      "delivery_status": "Unbekannt",
      "image_url": "https://medcanonestop.com/wp-content/themes/medcanonestop/assets/img/flower-icon.svg",
      "product_type": "Cannabisblüten",
      "timestamp": "2025-03-11T23:21:46.559478",
      "url": "https://medcanonestop.com/medcan_product/nimbus-26-1-zrp/"
    },
    {
      "title": "Nimbus 26/1 ZRP",
      "thc": {
        "value": 26.0,
        "unit": "%"
      },
      "cbd": {
        "value": 1.0,
        "unit": "%"
      },
      "price": {
        "value": {
          "value": null,
          "unit": null
        }
      },
      "delivery_status": "Unbekannt",
      "image_url": "https://medcanonestop.com/wp-content/themes/medcanonestop/assets/img/flower-icon.svg",
      "product_type": "Cannabisblüten",
      "timestamp": "2025-03-11T23:40:41.178753",
      "url": "https://medcanonestop.com/medcan_product/nimbus-26-1-zrp/"
    },
    {
      "title": "Nimbus 26/1 ZRP",
      "thc": {
        "value": 26.0,
        "unit": "%"
      },
      "cbd": {
        "value": 1.0,
        "unit": "%"
      },
      "price": {
        "value": {
          "value": null,
          "unit": null
        }
      },
      "delivery_status": "Unbekannt",
      "image_url": "https://medcanonestop.com/wp-content/themes/medcanonestop/assets/img/flower-icon.svg",
      "product_type": "Cannabisblüten",
      "timestamp": "2025-03-12T00:32:51.379883",
      "url": "https://medcanonestop.com/medcan_product/nimbus-26-1-zrp/"
    },
    {
      "title": "Nimbus 26/1 ZRP",
      "thc": {
        "value": 26.0,
        "unit": "%"
      },
      "cbd": {
        "value": 1.0,
        "unit": "%"
      },
      "price": {
        "value": {
          "value": null,
          "unit": null
        }
      },
      "delivery_status": "Unbekannt",
      "image_url": "https://medcanonestop.com/wp-content/themes/medcanonestop/assets/img/flower-icon.svg",
      "product_type": "Cannabisblüten",
      "timestamp": "2025-03-12T00:54:27.214665",
      "url": "https://medcanonestop.com/medcan_product/nimbus-26-1-zrp/"
    },
    {
      "title": "Nimbus 26/1 ZRP",
      "thc": {
        "value": 26.0,
        "unit": "%"
      },
      "cbd": {
        "value": 1.0,
        "unit": "%"
      },
      "price": {
        "value": {
          "value": null,
          "unit": null
        }
      },
      "delivery_status": "Unbekannt",
      "image_url": "https://medcanonestop.com/wp-content/themes/medcanonestop/assets/img/flower-icon.svg",
      "product_type": "Cannabisblüten",
      "timestamp": "2025-03-12T02:34:20.328406",
      "url": "https://medcanonestop.com/medcan_product/nimbus-26-1-zrp/"
    },
    {
      "title": "Nimbus 26/1 ZRP",
      "thc": {
        "value": 26.0,
        "unit": "%"
      },
      "cbd": {
        "value": 1.0,
        "unit": "%"
      },
      "price": {
        "value": {
          "value": null,
          "unit": null
        }
      },
      "delivery_status": "Unbekannt",
      "image_url": "https://medcanonestop.com/wp-content/themes/medcanonestop/assets/img/flower-icon.svg",
      "product_type": "Cannabisblüten",
      "timestamp": "2025-03-12T03:41:04.939333",
      "url": "https://medcanonestop.com/medcan_product/nimbus-26-1-zrp/"
    },
    {
      "title": "Nimbus 26/1 ZRP",
      "thc": {
        "value": 26.0,
        "unit": "%"
      },
      "cbd": {
        "value": 1.0,
        "unit": "%"
      },
      "price": {
        "value": {
          "value": null,
          "unit": null
        }
      },
      "delivery_status": "Unbekannt",
      "image_url": "https://medcanonestop.com/wp-content/themes/medcanonestop/assets/img/flower-icon.svg",
      "product_type": "Cannabisblüten",
      "timestamp": "2025-03-12T04:48:11.727190",
      "url": "https://medcanonestop.com/medcan_product/nimbus-26-1-zrp/"
    },
    {
      "title": "Nimbus 26/1 ZRP",
      "thc": {
        "value": 26.0,
        "unit": "%"
      },
      "cbd": {
        "value": 1.0,
        "unit": "%"
      },
      "price": {
        "value": {
          "value": null,
          "unit": null
        }
      },
      "delivery_status": "Unbekannt",
      "image_url": "https://medcanonestop.com/wp-content/themes/medcanonestop/assets/img/flower-icon.svg",
      "product_type": "Cannabisblüten",
      "timestamp": "2025-03-12T09:57:17.368622",
      "url": "https://medcanonestop.com/medcan_product/nimbus-26-1-zrp/"
    }
  ],
  "last_updated": "2025-03-12T09:57:17.368622"
}