{
  "title": "Pedanios 10/10 EQI CA",
  "thc": {
    "value": 10.0,
    "unit": "%"
  },
  "cbd": {
    "value": 10.0,
    "unit": "%"
  },
  "price": {
    "min": {
      "value": 6.69,
      "unit": "g"
    },
    "max": {
      "value": 16.42,
      "unit": "g"
    }
  },
  "delivery_status": "lieferbar",
  "image_url": "https://medcanonestop.com/wp-content/uploads/2023/12/Pedanios-10_10-EQI-CA_Bluete.png",
  "product_type": "Cannabisblüten",
  "timestamp": "2025-03-11T23:11:08.741794",
  "url": "https://medcanonestop.com/medcan_product/pedanios-10-10-eqi-ca-equiposa/",
  "history": [
    {
      "title": "Pedanios 10/10 EQI CA",
      "thc": {
        "value": 10.0,
        "unit": "%"
      },
      "cbd": {
        "value": 10.0,
        "unit": "%"
      },
      "price": {
        "min": {
          "value": 6.69,
          "unit": "g"
        },
        "max": {
          "value": 16.42,
          "unit": "g"
        }
      },
      "delivery_status": "lieferbar",
      "image_url": "https://medcanonestop.com/wp-content/uploads/2023/12/Pedanios-10_10-EQI-CA_Bluete.png",
      "product_type": "Cannabisblüten",
      "timestamp": "2025-03-11T23:28:12.780480",
      "url": "https://medcanonestop.com/medcan_product/pedanios-10-10-eqi-ca-equiposa/"
    },
    {
      "title": "Pedanios 10/10 EQI CA",
      "thc": {
        "value": 10.0,
        "unit": "%"
      },
      "cbd": {
        "value": 10.0,
        "unit": "%"
      },
      "price": {
        "min": {
          "value": 6.69,
          "unit": "g"
        },
        "max": {
          "value": 16.42,
          "unit": "g"
        }
      },
      "delivery_status": "lieferbar",
      "image_url": "https://medcanonestop.com/wp-content/uploads/2023/12/Pedanios-10_10-EQI-CA_Bluete.png",
      "product_type": "Cannabisblüten",
      "timestamp": "2025-03-11T23:49:02.481347",
      "url": "https://medcanonestop.com/medcan_product/pedanios-10-10-eqi-ca-equiposa/"
    },
    {
      "title": "Pedanios 10/10 EQI CA",
      "thc": {
        "value": 10.0,
        "unit": "%"
      },
      "cbd": {
        "value": 10.0,
        "unit": "%"
      },
      "price": {
        "min": {
          "value": 6.69,
          "unit": "g"
        },
        "max": {
          "value": 16.42,
          "unit": "g"
        }
      },
      "delivery_status": "lieferbar",
      "image_url": "https://medcanonestop.com/wp-content/uploads/2023/12/Pedanios-10_10-EQI-CA_Bluete.png",
      "product_type": "Cannabisblüten",
      "timestamp": "2025-03-12T00:08:43.290355",
      "url": "https://medcanonestop.com/medcan_product/pedanios-10-10-eqi-ca-equiposa/"
    },
    {
      "title": "Pedanios 10/10 EQI CA",
      "thc": {
        "value": 10.0,
        "unit": "%"
      },
      "cbd": {
        "value": 10.0,
        "unit": "%"
      },
      "price": {
        "min": {
          "value": 6.69,
          "unit": "g"
        },
        "max": {
          "value": 16.42,
          "unit": "g"
        }
      },
      "delivery_status": "lieferbar",
      "image_url": "https://medcanonestop.com/wp-content/uploads/2023/12/Pedanios-10_10-EQI-CA_Bluete.png",
      "product_type": "Cannabisblüten",
      "timestamp": "2025-03-12T00:27:49.983682",
      "url": "https://medcanonestop.com/medcan_product/pedanios-10-10-eqi-ca-equiposa/"
    },
    {
      "title": "Pedanios 10/10 EQI CA",
      "thc": {
        "value": 10.0,
        "unit": "%"
      },
      "cbd": {
        "value": 10.0,
        "unit": "%"
      },
      "price": {
        "min": {
          "value": 6.69,
          "unit": "g"
        },
        "max": {
          "value": 16.42,
          "unit": "g"
        }
      },
      "delivery_status": "lieferbar",
      "image_url": "https://medcanonestop.com/wp-content/uploads/2023/12/Pedanios-10_10-EQI-CA_Bluete.png",
      "product_type": "Cannabisblüten",
      "timestamp": "2025-03-12T00:50:03.176485",
      "url": "https://medcanonestop.com/medcan_product/pedanios-10-10-eqi-ca-equiposa/"
    },
    {
      "title": "Pedanios 10/10 EQI CA",
      "thc": {
        "value": 10.0,
        "unit": "%"
      },
      "cbd": {
        "value": 10.0,
        "unit": "%"
      },
      "price": {
        "min": {
          "value": 6.69,
          "unit": "g"
        },
        "max": {
          "value": 16.42,
          "unit": "g"
        }
      },
      "delivery_status": "lieferbar",
      "image_url": "https://medcanonestop.com/wp-content/uploads/2023/12/Pedanios-10_10-EQI-CA_Bluete.png",
      "product_type": "Cannabisblüten",
      "timestamp": "2025-03-12T02:16:24.154756",
      "url": "https://medcanonestop.com/medcan_product/pedanios-10-10-eqi-ca-equiposa/"
    },
    {
      "title": "Pedanios 10/10 EQI CA",
      "thc": {
        "value": 10.0,
        "unit": "%"
      },
      "cbd": {
        "value": 10.0,
        "unit": "%"
      },
      "price": {
        "min": {
          "value": 6.69,
          "unit": "g"
        },
        "max": {
          "value": 16.42,
          "unit": "g"
        }
      },
      "delivery_status": "lieferbar",
      "image_url": "https://medcanonestop.com/wp-content/uploads/2023/12/Pedanios-10_10-EQI-CA_Bluete.png",
      "product_type": "Cannabisblüten",
      "timestamp": "2025-03-12T02:34:21.718872",
      "url": "https://medcanonestop.com/medcan_product/pedanios-10-10-eqi-ca-equiposa/"
    },
    {
      "title": "Pedanios 10/10 EQI CA",
      "thc": {
        "value": 10.0,
        "unit": "%"
      },
      "cbd": {
        "value": 10.0,
        "unit": "%"
      },
      "price": {
        "min": {
          "value": 6.69,
          "unit": "g"
        },
        "max": {
          "value": 16.42,
          "unit": "g"
        }
      },
      "delivery_status": "lieferbar",
      "image_url": "https://medcanonestop.com/wp-content/uploads/2023/12/Pedanios-10_10-EQI-CA_Bluete.png",
      "product_type": "Cannabisblüten",
      "timestamp": "2025-03-12T03:41:06.698961",
      "url": "https://medcanonestop.com/medcan_product/pedanios-10-10-eqi-ca-equiposa/"
    },
    {
      "title": "Pedanios 10/10 EQI CA",
      "thc": {
        "value": 10.0,
        "unit": "%"
      },
      "cbd": {
        "value": 10.0,
        "unit": "%"
      },
      "price": {
        "min": {
          "value": 6.69,
          "unit": "g"
        },
        "max": {
          "value": 16.42,
          "unit": "g"
        }
      },
      "delivery_status": "lieferbar",
      "image_url": "https://medcanonestop.com/wp-content/uploads/2023/12/Pedanios-10_10-EQI-CA_Bluete.png",
      "product_type": "Cannabisblüten",
      "timestamp": "2025-03-12T04:48:14.322478",
      "url": "https://medcanonestop.com/medcan_product/pedanios-10-10-eqi-ca-equiposa/"
    }
  ],
  "last_updated": "2025-03-12T04:48:14.322478"
}